README.md
setup.py
confj/__init__.py
confj/conf.py
confj/confdata.py
confj/const.py
confj/exceptions.py
confj/validation.py
confj.egg-info/PKG-INFO
confj.egg-info/SOURCES.txt
confj.egg-info/dependency_links.txt
confj.egg-info/requires.txt
confj.egg-info/top_level.txt