Metadata-Version: 2.1
Name: confj
Version: 0.2.2
Summary: Load configs from json files
Home-page: https://github.com/aleosd/confj
Author: Alekey Osadchuk
Author-email: osdalex@gmail.com
License: UNKNOWN
Project-URL: Bug Reports, https://github.com/aleosd/confj/issues
Project-URL: Say Thanks!, https://saythanks.io/to/aleosd
Project-URL: Source, https://github.com/aleosd/confj/
Keywords: json configs loader
Platform: UNKNOWN
Classifier: Development Status :: 4 - Beta
Classifier: Intended Audience :: Developers
Classifier: Topic :: Software Development :: Build Tools
Classifier: License :: OSI Approved :: MIT License
Classifier: Programming Language :: Python :: 2
Classifier: Programming Language :: Python :: 2.7
Classifier: Programming Language :: Python :: 3
Classifier: Programming Language :: Python :: 3.4
Classifier: Programming Language :: Python :: 3.5
Classifier: Programming Language :: Python :: 3.6
Classifier: Programming Language :: Python :: 3.7
Requires-Python: >=3.5, <4
Provides-Extra: test
Provides-Extra: validation
